ShelfCMS-0.12.25.dist-info/DESCRIPTION.rst
ShelfCMS-0.12.25.dist-info/METADATA
ShelfCMS-0.12.25.dist-info/RECORD
ShelfCMS-0.12.25.dist-info/WHEEL
ShelfCMS-0.12.25.dist-info/metadata.json
ShelfCMS-0.12.25.dist-info/top_level.txt
examples/__init__.py
examples/fulltest/__init__.py
examples/fulltest/admin.py
examples/fulltest/app.py
examples/fulltest/config.py
examples/fulltest/filters.py
examples/fulltest/manage.py
examples/fulltest/models.py
examples/fulltest/view.py
shelf/__init__.py
shelf/base.py
shelf/manager.py
shelf/admin/__init__.py
shelf/admin/actions.py
shelf/admin/base.py
shelf/admin/field.py
shelf/admin/form.py
shelf/admin/view.py
shelf/admin/widget.py
shelf/plugins/__init__.py
shelf/plugins/analytics/__init__.py
shelf/plugins/blueprint/__init__.py
shelf/plugins/dashboard/__init__.py
shelf/plugins/dashboard/provider.py
shelf/plugins/dashboard/widget.py
shelf/plugins/dashboard/static/dashboard.css
shelf/plugins/dashboard/static/masonry.min.js
shelf/plugins/dashboard/static/morris.css
shelf/plugins/dashboard/static/morris.min.js
shelf/plugins/dashboard/static/raphael-min.js
shelf/plugins/dashboard/templates/bar.html
shelf/plugins/dashboard/templates/dashboard.html
shelf/plugins/dashboard/templates/donut.html
shelf/plugins/dashboard/templates/evolution.html
shelf/plugins/dashboard/templates/picture-text.html
shelf/plugins/dashboard/templates/simple-text.html
shelf/plugins/ecommerce/__init__.py
shelf/plugins/ecommerce/abstract_models.py
shelf/plugins/ecommerce/abstract_views.py
shelf/plugins/ecommerce/models.py
shelf/plugins/ecommerce/views.py
shelf/plugins/ecommerce/templates/client.html
shelf/plugins/ecommerce/templates/client.list-actions.html
shelf/plugins/ecommerce/templates/order-list.html
shelf/plugins/ecommerce/templates/order.html
shelf/plugins/i18n/__init__.py
shelf/plugins/i18n/templates/localized-widget.html
shelf/plugins/i18n/templates/shelf-i18n-field-tail.html
shelf/plugins/library/__init__.py
shelf/plugins/library/static/jquery.file.js
shelf/plugins/library/static/smartcrop.js
shelf/plugins/library/templates/shelf-field-file.html
shelf/plugins/library/templates/shelf-field-picture-path.html
