Metadata-Version: 2.0
Name: ShelfCMS
Version: 0.12.25
Summary: Enhancing flask microframework with beautiful admin
Home-page: https://github.com/iriahi/shelf-cms
Author: Ismael Riahi
Author-email: ismael@batb.fr
License: BSD
Platform: UNKNOWN
Classifier: License :: OSI Approved :: BSD License
Classifier: Intended Audience :: Developers
Classifier: Development Status :: 4 - Beta
Classifier: Environment :: Web Environment
Classifier: Framework :: Flask
Classifier: Topic :: Software Development :: Build Tools
Classifier: Topic :: Software Development :: User Interfaces
Classifier: Topic :: Internet :: WWW/HTTP :: Dynamic Content
Classifier: Programming Language :: Python :: 2
Classifier: Programming Language :: Python :: 2.7
Requires-Dist: Flask
Requires-Dist: Flask-Admin
Requires-Dist: Flask-Babel
Requires-Dist: Flask-Images
Requires-Dist: Flask-Principal
Requires-Dist: Flask-SQLAlchemy
Requires-Dist: Flask-Script
Requires-Dist: Flask-Security
Requires-Dist: Flask-WTF
Requires-Dist: Jinja2
Requires-Dist: Pillow
Requires-Dist: SQLAlchemy
Requires-Dist: SQLAlchemy-Defaults
Requires-Dist: SQLAlchemy-Utils
Requires-Dist: WTForms
Requires-Dist: WTForms-Alchemy
Requires-Dist: Werkzeug
Requires-Dist: bcrypt
Requires-Dist: google-api-python-client
Requires-Dist: humanize
Requires-Dist: prices
Requires-Dist: pyOpenSSL
Provides-Extra: dev
Requires-Dist: codecov; extra == 'dev'
Requires-Dist: coverage; extra == 'dev'
Requires-Dist: imgurpython; extra == 'dev'
Requires-Dist: nose; extra == 'dev'
Requires-Dist: scripttest; extra == 'dev'
Requires-Dist: selenium; extra == 'dev'
